balinese_nlp/__init__.py
balinese_nlp/corefresolution/__init__.py
balinese_nlp/corefresolution/rule_based/CoreferenceResolution.py
balinese_nlp/corefresolution/rule_based/LinkedList.py
balinese_nlp/corefresolution/rule_based/__init__.py
balinese_nlp/embeddings/BasePretrained.py
balinese_nlp/embeddings/__init__.py
balinese_nlp/embeddings/BERT/BalimultiLingBERT.py
balinese_nlp/embeddings/BERT/__init__.py
balinese_nlp/embeddings/TFIDF/BaliTFIDF.py
balinese_nlp/embeddings/TFIDF/__init__.py
balinese_nlp/embeddings/TFISF/BaliTFISF.py
balinese_nlp/embeddings/TFISF/__init__.py
balinese_nlp/embeddings/gensims/BaliFastText.py
balinese_nlp/embeddings/gensims/BaliWord2Vec.py
balinese_nlp/embeddings/gensims/__init__.py
balinese_nlp/embeddings/gloves/BaliGlove.py
balinese_nlp/embeddings/gloves/Glove.py
balinese_nlp/embeddings/gloves/__init__.py
balinese_nlp/feature_extractor/__init__.py
balinese_nlp/feature_extractor/data/__init__.py
balinese_nlp/feature_extractor/data/booster_words.txt
balinese_nlp/feature_extractor/data/negation_words.txt
balinese_nlp/feature_extractor/narratives/__init__.py
balinese_nlp/feature_extractor/narratives/characterclassification/BaseModelFeatureExtraction.py
balinese_nlp/feature_extractor/narratives/characterclassification/FeatureExtraction.py
balinese_nlp/feature_extractor/narratives/characterclassification/LexiconFeatureExtraction.py
balinese_nlp/feature_extractor/narratives/characterclassification/POSTagFeatureExtraction.py
balinese_nlp/feature_extractor/narratives/characterclassification/WordEmbeddingFeatureExtraction.py
balinese_nlp/feature_extractor/narratives/characterclassification/__init__.py
balinese_nlp/feature_extractor/summarization/FeatureExtractor.py
balinese_nlp/feature_extractor/summarization/TFISFVectorizer.py
balinese_nlp/feature_extractor/summarization/__init__.py
balinese_nlp/narratives/__init__.py
balinese_nlp/narratives/utils.py
balinese_nlp/narratives/aliasclustering/__init__.py
balinese_nlp-2.2.0.dist-info/LICENSE
balinese_nlp-2.2.0.dist-info/METADATA
balinese_nlp-2.2.0.dist-info/WHEEL
balinese_nlp-2.2.0.dist-info/top_level.txt
balinese_nlp-2.2.0.dist-info/RECORD
