Metadata-Version: 2.1
Name: balinese_nlp
Version: 2.2.0
Summary: A comprehensive Python package tools for Balinese Natural Language Processing
Author: I Made Satria Bimantara
Author-email: satriabimantara@unud.ac.id
Keywords: Balinese,NLP,Text Preprocessing,Semantic Feature Extraction,Embedding Models,Narrative Analysis,NER,POS Tagging,Summarization
Classifier: Development Status :: 4 - Beta
Classifier: Intended Audience :: Developers
Classifier: Intended Audience :: Science/Research
Classifier: License :: OSI Approved :: BSD License
Classifier: Programming Language :: Python :: 3
Classifier: Programming Language :: Python :: 3.8
Classifier: Operating System :: OS Independent
Classifier: Natural Language :: Indonesian
Classifier: Topic :: Text Processing :: Linguistic
Classifier: Topic :: Scientific/Engineering :: Artificial Intelligence
Requires-Python: >=3.8
License-File: LICENSE
Requires-Dist: gensim ==4.3.3
Requires-Dist: huggingface-hub ==0.33.0
Requires-Dist: scikit-learn ==1.2.1
Requires-Dist: matplotlib ==3.6.3
Requires-Dist: matplotlib-inline ==0.1.6
Requires-Dist: nltk
Requires-Dist: transformers ==4.33.3
Requires-Dist: torch ==2.3.0
Requires-Dist: pandas ==1.5.3
Requires-Dist: jaro-winkler ==2.0.3
Requires-Dist: sklearn-crfsuite ==0.3.6
Requires-Dist: hmmlearn ==0.3.0
Requires-Dist: statsmodels ==0.14.1
Requires-Dist: krippendorff ==0.6.0
Requires-Dist: openpyxl ==3.1.5
